Metadata-Version: 2.4
Name: carl-bench
Version: 1.1.1
Summary: Benchmark for contextual RL
Author: Carolin Benjamins, Frederik Schubert, André Biedenkapp, Sebastian Döhler
Author-email: Theresa Eimer <t.eimer@ai.uni-hannover.de>, Aditya Mohan <a.mohan@ai.uni-hannover.de>
License:                                  Apache License
Project-URL: Homepage, https://github.com/automl/CARL
Project-URL: Documentation, https://automl.github.io/CARL/main/
Project-URL: Repository, https://github.com/automl/CARL
Project-URL: Issues, https://github.com/automl/CARL/issues
Keywords: RL,Generalization
Classifier: Programming Language :: Python :: 3
Classifier: Natural Language :: English
Classifier: Environment :: Console
Classifier: Intended Audience :: Developers
Classifier: Intended Audience :: Education
Classifier: Intended Audience :: Science/Research
Classifier: License :: OSI Approved :: Apache Software License
Classifier: Operating System :: POSIX :: Linux
Classifier: Topic :: Scientific/Engineering :: Artificial Intelligence
Classifier: Topic :: Scientific/Engineering
Classifier: Topic :: Software Development
Requires-Python: >=3.9
License-File: LICENSE
Requires-Dist: gym
Requires-Dist: gymnasium<1.0.0
Requires-Dist: pygame
Requires-Dist: scipy>=1.7.0
Requires-Dist: ConfigArgParse>=1.5.1
Requires-Dist: numpy>=1.19.5
Requires-Dist: pandas>=1.3.0
Requires-Dist: matplotlib>=3.4.2
Requires-Dist: dataclasses>=0.6
Requires-Dist: numpyencoder>=0.3.0
Requires-Dist: pyglet>=1.5.15
Requires-Dist: pytablewriter>=0.62.0
Requires-Dist: PyYAML>=5.4.1
Requires-Dist: tabulate>=0.8.9
Requires-Dist: bs4>=0.0.1
Requires-Dist: configspace>=1.2.1
Requires-Dist: omegaconf>=2.3.0
Provides-Extra: box2d
Requires-Dist: gymnasium[box2d]<1.0.0; extra == "box2d"
Provides-Extra: brax
Requires-Dist: brax==0.12.1; extra == "brax"
Requires-Dist: protobuf>=3.17.3; extra == "brax"
Provides-Extra: dm-control
Requires-Dist: dm_control>=1.0.3; extra == "dm-control"
Provides-Extra: mario
Requires-Dist: opencv-python>=4.8.0; extra == "mario"
Requires-Dist: torch~=2.4.1; extra == "mario"
Requires-Dist: Pillow>=8.3.1; extra == "mario"
Requires-Dist: py4j>=0.10.9.2; extra == "mario"
Requires-Dist: pyvirtualdisplay>=3.0; extra == "mario"
Requires-Dist: jdk4py>=17.0.7.0; extra == "mario"
Provides-Extra: all-envs
Requires-Dist: opencv-python>=4.8.0; extra == "all-envs"
Requires-Dist: torch~=2.4.1; extra == "all-envs"
Requires-Dist: Pillow>=8.3.1; extra == "all-envs"
Requires-Dist: py4j>=0.10.9.2; extra == "all-envs"
Requires-Dist: pyvirtualdisplay>=3.0; extra == "all-envs"
Requires-Dist: jdk4py>=17.0.7.0; extra == "all-envs"
Requires-Dist: gymnasium[box2d]>=0.27.1; extra == "all-envs"
Requires-Dist: brax==0.12.1; extra == "all-envs"
Requires-Dist: protobuf>=3.17.3; extra == "all-envs"
Requires-Dist: dm_control>=1.0.3; extra == "all-envs"
Provides-Extra: dev
Requires-Dist: pytest>=6.1.1; extra == "dev"
Requires-Dist: pytest-cov; extra == "dev"
Requires-Dist: mypy; extra == "dev"
Requires-Dist: ruff; extra == "dev"
Requires-Dist: isort; extra == "dev"
Requires-Dist: pydocstyle; extra == "dev"
Requires-Dist: pre-commit; extra == "dev"
Provides-Extra: docs
Requires-Dist: sphinx>=4.2.0; extra == "docs"
Requires-Dist: sphinx-gallery>=0.10.0; extra == "docs"
Requires-Dist: image>=1.5.33; extra == "docs"
Requires-Dist: sphinx-autoapi>=1.8.4; extra == "docs"
Requires-Dist: automl-sphinx-theme>=0.1.9; extra == "docs"
Provides-Extra: examples
Requires-Dist: stable-baselines3; extra == "examples"
Provides-Extra: all
Requires-Dist: ioh==0.3.17; extra == "all"
Requires-Dist: modcma==1.0.8; extra == "all"
Requires-Dist: torchvision==0.19.1; extra == "all"
Requires-Dist: torch==2.4.1; extra == "all"
Requires-Dist: uuid; extra == "all"
Dynamic: license-file
